slot_machine/__init__.py
slot_machine/samplers.py
slot_machine/serializers.py
slot_machine_serializers-0.4.1.dist-info/METADATA
slot_machine_serializers-0.4.1.dist-info/WHEEL
slot_machine_serializers-0.4.1.dist-info/top_level.txt
slot_machine_serializers-0.4.1.dist-info/RECORD
