Metadata-Version: 2.1
Name: slot-machine-serializers
Version: 0.4.1
Summary: Ordered dataclass serializer mixin for sloted dataclasses
Home-page: https://github.com/sirno/slot_machine
License: MIT
Requires-Dist: pyyaml
Requires-Dist: typing-extensions
Provides-Extra: dev
Requires-Dist: pytest ; extra == 'dev'
Requires-Dist: black ; extra == 'dev'
Requires-Dist: tox ; extra == 'dev'
